stitch_api/__init__.py
stitch_api/cli.py
stitch_api/constants.py
stitch_api/stitch_api.py
stitch_api/api/__init__.py
stitch_api/api/common.py
stitch_api/api/internal.py
stitch_api/api/public.py
python_stitch_data-0.1.4.dist-info/LICENSE
python_stitch_data-0.1.4.dist-info/METADATA
python_stitch_data-0.1.4.dist-info/WHEEL
python_stitch_data-0.1.4.dist-info/entry_points.txt
python_stitch_data-0.1.4.dist-info/top_level.txt
python_stitch_data-0.1.4.dist-info/RECORD
