Metadata-Version: 2.1
Name: python-stitch-data
Version: 0.1.4
Summary: Python wrapper for Stitch Data API
Home-page: https://github.com/rynmccrmck/python-stitch-data
License: UNKNOWN
Download-URL: https://github.com/rynmccrmck/python-stitch-data/archive/v0.1.4.tar.gz
Keywords: stitch,api,wrapper
Platform: UNKNOWN
Requires-Dist: click
Requires-Dist: python-dotenv
Requires-Dist: requests-toolbelt
